consent/__init__.py
consent/templates/consent/banner.html
consent/templatetags/__init__.py
consent/templatetags/consent_tags.py
django_monitor_consent-1.1.dist-info/LICENSE
django_monitor_consent-1.1.dist-info/METADATA
django_monitor_consent-1.1.dist-info/WHEEL
django_monitor_consent-1.1.dist-info/top_level.txt
django_monitor_consent-1.1.dist-info/RECORD
