Metadata-Version: 2.1
Name: django-monitor-consent
Version: 1.1
Summary: Django app for displaying a consent to monitoring banner
Home-page: https://github.com/cash/django-monitor-consent
Author: Cash Costello
Author-email: cash.costello@gmail.com
License: BSD
Platform: UNKNOWN
Classifier: Development Status :: 5 - Production/Stable
Classifier: Environment :: Web Environment
Classifier: Intended Audience :: Developers
Classifier: License :: OSI Approved :: BSD License
Classifier: Programming Language :: Python :: 3
Requires-Python: >=3.6
